{
  "hash": "a1dcbf73",
  "browserHash": "e8abdced",
  "optimized": {
    "react": {
      "src": "../../node_modules/react/index.js",
      "file": "react.js",
      "fileHash": "29f229a6",
      "needsInterop": true
    },
    "react-dom": {
      "src": "../../node_modules/react-dom/index.js",
      "file": "react-dom.js",
      "fileHash": "23fdddcb",
      "needsInterop": true
    },
    "react/jsx-dev-runtime": {
      "src": "../../node_modules/react/jsx-dev-runtime.js",
      "file": "react_jsx-dev-runtime.js",
      "fileHash": "79ce37df",
      "needsInterop": true
    },
    "react/jsx-runtime": {
      "src": "../../node_modules/react/jsx-runtime.js",
      "file": "react_jsx-runtime.js",
      "fileHash": "d9e08bd9",
      "needsInterop": true
    },
    "framer-motion": {
      "src": "../../node_modules/framer-motion/dist/es/index.mjs",
      "file": "framer-motion.js",
      "fileHash": "e027a336",
      "needsInterop": false
    },
    "react-dom/client": {
      "src": "../../node_modules/react-dom/client.js",
      "file": "react-dom_client.js",
      "fileHash": "4c9a2fc9",
      "needsInterop": true
    },
    "react-icons/fa": {
      "src": "../../node_modules/react-icons/fa/index.esm.js",
      "file": "react-icons_fa.js",
      "fileHash": "a75b23af",
      "needsInterop": false
    },
    "react-icons/si": {
      "src": "../../node_modules/react-icons/si/index.esm.js",
      "file": "react-icons_si.js",
      "fileHash": "509f34d5",
      "needsInterop": false
    }
  },
  "chunks": {
    "chunk-EU4VESBO": {
      "file": "chunk-EU4VESBO.js"
    },
    "chunk-FGCE2R2A": {
      "file": "chunk-FGCE2R2A.js"
    },
    "chunk-KRQVU3GS": {
      "file": "chunk-KRQVU3GS.js"
    }
  }
}